carbonintensity/__init__.py
carbonintensity/client.py
carbonintensity-0.3.0.dist-info/LICENSE
carbonintensity-0.3.0.dist-info/METADATA
carbonintensity-0.3.0.dist-info/WHEEL
carbonintensity-0.3.0.dist-info/top_level.txt
carbonintensity-0.3.0.dist-info/RECORD
