Metadata-Version: 2.1
Name: carbonintensity
Version: 0.3.0
Summary: Home Assistant Client library for Carbon Intensity API
Home-page: https://github.com/jscruz/carbonintensity
Author: Jorge Cruz Lambert
Author-email: jscl@pm.me
License: UNKNOWN
Platform: UNKNOWN
Classifier: Programming Language :: Python :: 3
Classifier: License :: OSI Approved :: MIT License
Classifier: Operating System :: OS Independent
Requires-Dist: aiohttp
Provides-Extra: test
Requires-Dist: pytest ; extra == 'test'
Requires-Dist: pytest-asyncio ; extra == 'test'
Requires-Dist: aiohttp ; extra == 'test'
